aiokatcp/__init__.py
aiokatcp/_version.py
aiokatcp/adjtimex.py
aiokatcp/client.py
aiokatcp/connection.py
aiokatcp/core.py
aiokatcp/py.typed
aiokatcp/sensor.py
aiokatcp/server.py
aiokatcp/time_sync.py
aiokatcp/tools/__init__.py
aiokatcp/tools/katcpcmd.py
aiokatcp-2.1.0.dist-info/licenses/LICENSE.txt
aiokatcp-2.1.0.dist-info/METADATA
aiokatcp-2.1.0.dist-info/WHEEL
aiokatcp-2.1.0.dist-info/entry_points.txt
aiokatcp-2.1.0.dist-info/top_level.txt
aiokatcp-2.1.0.dist-info/RECORD
