Metadata-Version: 2.4
Name: aiokatcp
Version: 2.1.0
Summary: Asynchronous I/O implementation of the katcp protocol
Author-email: Bruce Merry <bmerry@sarao.ac.za>
License: BSD-3-Clause
Project-URL: Homepage, https://github.com/ska-sa/aiokatcp
Project-URL: Repository, https://github.com/ska-sa/aiokatcp
Project-URL: Documentation, https://aiokatcp.readthedocs.io/
Project-URL: Changelog, https://aiokatcp.readthedocs.io/en/latest/changelog.html
Keywords: asyncio,katcp
Classifier: Development Status :: 5 - Production/Stable
Classifier: Intended Audience :: Developers
Classifier: Framework :: AsyncIO
Classifier: License :: OSI Approved :: BSD License
Classifier: Operating System :: OS Independent
Classifier: Programming Language :: Python :: 3
Classifier: Topic :: Software Development :: Libraries :: Python Modules
Classifier: Topic :: Scientific/Engineering :: Astronomy
Requires-Python: >=3.8
License-File: LICENSE.txt
Requires-Dist: async-timeout>=1.3.0
Requires-Dist: decorator>=4.1
Requires-Dist: katcp-codec
Requires-Dist: typing-extensions
Provides-Extra: test
Requires-Dist: async-solipsism>=0.6; extra == "test"
Requires-Dist: hypothesis; extra == "test"
Requires-Dist: pytest; extra == "test"
Requires-Dist: pytest-asyncio>=0.23; extra == "test"
Requires-Dist: pytest-mock; extra == "test"
Provides-Extra: doc
Requires-Dist: sphinx; extra == "doc"
Requires-Dist: sphinx-rtd-theme; extra == "doc"
Dynamic: license-file
